about/__init__.py
about/admin.py
about/apps.py
about/cache_utils.py
about/conf.py
about/urls.py
about/version_utils.py
about/views.py
about/templates/about/dashboard.html
django_about-0.1.2.dist-info/licenses/LICENSE
django_about-0.1.2.dist-info/METADATA
django_about-0.1.2.dist-info/WHEEL
django_about-0.1.2.dist-info/top_level.txt
django_about-0.1.2.dist-info/RECORD
