Metadata-Version: 2.4
Name: django-about
Version: 0.1.2
Summary: A customizable Django app that displays system version information in the admin interface
Author-email: Mark Cervarich <645942+markcerv@users.noreply.github.com>
License: MIT
Project-URL: Homepage, https://github.com/markcerv/django-about
Project-URL: Documentation, https://github.com/markcerv/django-about#readme
Project-URL: Repository, https://github.com/markcerv/django-about
Project-URL: Issues, https://github.com/markcerv/django-about/issues
Project-URL: Changelog, https://github.com/markcerv/django-about/blob/main/CHANGELOG.md
Keywords: django,admin,system,version,information,monitoring
Classifier: Development Status :: 4 - Beta
Classifier: Environment :: Web Environment
Classifier: Framework :: Django
Classifier: Framework :: Django :: 3.2
Classifier: Framework :: Django :: 4.0
Classifier: Framework :: Django :: 4.1
Classifier: Framework :: Django :: 4.2
Classifier: Framework :: Django :: 5.0
Classifier: Framework :: Django :: 5.1
Classifier: Framework :: Django :: 5.2
Classifier: Intended Audience :: Developers
Classifier: License :: OSI Approved :: MIT License
Classifier: Operating System :: OS Independent
Classifier: Programming Language :: Python
Classifier: Programming Language :: Python :: 3
Classifier: Programming Language :: Python :: 3.8
Classifier: Programming Language :: Python :: 3.9
Classifier: Programming Language :: Python :: 3.10
Classifier: Programming Language :: Python :: 3.11
Classifier: Programming Language :: Python :: 3.12
Classifier: Topic :: Internet :: WWW/HTTP
Classifier: Topic :: Internet :: WWW/HTTP :: Dynamic Content
Classifier: Topic :: Software Development :: Libraries :: Python Modules
Requires-Python: >=3.8
License-File: LICENSE
Requires-Dist: django>=3.2
Provides-Extra: dev
Requires-Dist: pytest>=7.0; extra == "dev"
Requires-Dist: pytest-django>=4.0; extra == "dev"
Requires-Dist: black>=23.0; extra == "dev"
Requires-Dist: isort>=5.0; extra == "dev"
Requires-Dist: flake8>=6.0; extra == "dev"
Dynamic: license-file
